dsw/command_queue/__init__.py
dsw/command_queue/build_info.py
dsw/command_queue/command_queue.py
dsw/command_queue/query.py
dsw_command_queue-4.26.1.dist-info/licenses/LICENSE
dsw_command_queue-4.26.1.dist-info/METADATA
dsw_command_queue-4.26.1.dist-info/WHEEL
dsw_command_queue-4.26.1.dist-info/top_level.txt
dsw_command_queue-4.26.1.dist-info/RECORD
