Metadata-Version: 2.4
Name: dsw-command-queue
Version: 4.26.1
Summary: Library for working with command queue and persistent commands
Author-email: Marek Suchánek <marek.suchanek@ds-wizard.org>
License: Apache License 2.0
Project-URL: Homepage, https://ds-wizard.org
Project-URL: Repository, https://github.com/ds-wizard/engine-tools
Project-URL: Documentation, https://guide.ds-wizard.org
Keywords: dsw,subscriber,publisher,database,queue,processing
Classifier: Development Status :: 5 - Production/Stable
Classifier: License :: OSI Approved :: Apache Software License
Classifier: Programming Language :: Python
Classifier: Programming Language :: Python :: 3.12
Classifier: Programming Language :: Python :: 3.13
Classifier: Topic :: Database
Classifier: Topic :: Text Processing
Classifier: Topic :: Utilities
Requires-Python: <4,>=3.12
License-File: LICENSE
Requires-Dist: func-timeout
Requires-Dist: dsw-database==4.26.1
Dynamic: license-file
